music_album_creation/__init__.py
music_album_creation/__main__.py
music_album_creation/_logging.py
music_album_creation/audio_segmentation/__init__.py
music_album_creation/audio_segmentation/album_segmentation.py
music_album_creation/audio_segmentation/data.py
music_album_creation/create_album.py
music_album_creation/dialogs.py
music_album_creation/downloading.py
music_album_creation/ffmpeg/__init__.py
music_album_creation/ffmpeg/ffmpeg/__init__.py
music_album_creation/ffmpeg/ffmpeg/ffmpeg.py
music_album_creation/ffmpeg/ffmpeg/ffmpeg_proxy.py
music_album_creation/ffmpeg/ffmpeg/ffmpeg_subject.py
music_album_creation/ffmpeg/ffprobe/__init__.py
music_album_creation/ffmpeg/ffprobe/ffprobe.py
music_album_creation/ffmpeg/ffprobe/ffprobe_proxy.py
music_album_creation/ffmpeg/ffprobe/ffprobe_subject.py
music_album_creation/ffmpeg/run_cli.py
music_album_creation/ffprobe_client.py
music_album_creation/logging.ini
music_album_creation/metadata.py
music_album_creation/music_master.py
music_album_creation/tracks_parsing.py
music_album_creation/web_parsing.py
music_album_creation-1.4.0.dist-info/LICENSE
music_album_creation-1.4.0.dist-info/LICENSE.txt
music_album_creation-1.4.0.dist-info/METADATA
music_album_creation-1.4.0.dist-info/WHEEL
music_album_creation-1.4.0.dist-info/entry_points.txt
music_album_creation-1.4.0.dist-info/RECORD
