Metadata-Version: 2.1
Name: music-album-creation
Version: 1.4.0
Summary: A CLI application intending to automate offline music library building
Home-page: https://github.com/boromir674/music-album-creator
License: AGPL-3.0-only
Keywords: youtube,download,music,automation,metadata,cli,python package
Author: Konstantinos Lampridis
Author-email: k.lampridis@hotmail.com
Requires-Python: >=3.8,<4.0
Classifier: Development Status :: 5 - Production/Stable
Classifier: Intended Audience :: Developers
Classifier: Intended Audience :: End Users/Desktop
Classifier: License :: OSI Approved :: GNU Affero General Public License v3
Classifier: Natural Language :: English
Classifier: Operating System :: Microsoft :: Windows
Classifier: Operating System :: POSIX :: Linux
Classifier: Operating System :: Unix
Classifier: Programming Language :: Python :: 3
Classifier: Programming Language :: Python :: 3.8
Classifier: Programming Language :: Python :: 3.9
Classifier: Programming Language :: Python :: 3.10
Classifier: Programming Language :: Python :: 3.11
Classifier: Programming Language :: Python :: 2
Classifier: Programming Language :: Python :: 2.7
Classifier: Programming Language :: Python :: 3
Classifier: Programming Language :: Python :: 3.5
Classifier: Programming Language :: Python :: 3.6
Classifier: Programming Language :: Python :: 3.7
Classifier: Topic :: Home Automation
Classifier: Topic :: Multimedia :: Sound/Audio
Classifier: Topic :: Multimedia :: Video :: Conversion
Classifier: Topic :: Software Development
Classifier: Topic :: Software Development :: Libraries :: Python Modules
Classifier: Topic :: System :: Software Distribution
Classifier: Typing :: Typed
Provides-Extra: docs
Provides-Extra: notebook
Provides-Extra: test
Provides-Extra: typing
Requires-Dist: attrs (>=22.1.0,<23.0.0)
Requires-Dist: click (>=8.1.3,<9.0.0)
Requires-Dist: jupyter (>=1.0.0,<2.0.0) ; extra == "notebook"
Requires-Dist: matplotlib (>=3.6.2,<4.0.0) ; extra == "notebook"
Requires-Dist: mutagen (>=1.46.0,<2.0.0)
Requires-Dist: mypy (>=1.1.1,<2.0.0) ; extra == "typing"
Requires-Dist: prompt-toolkit (>=3.0.33,<4.0.0) ; extra == "notebook"
Requires-Dist: pyreadline (>=2.1,<3.0)
Requires-Dist: pytest (>=7.2.0,<8.0.0) ; extra == "test"
Requires-Dist: pytest-click (>=1.1.0,<2.0.0) ; extra == "test"
Requires-Dist: pytest-cov (>=4.0.0,<5.0.0) ; extra == "test"
Requires-Dist: pytest-explicit (>=1.0.1,<2.0.0) ; extra == "test"
Requires-Dist: pytest-object-getter (>=1.0.2,<2.0.0) ; extra == "test"
Requires-Dist: pytest-run-subprocess (>=0.10.0,<0.11.0) ; extra == "test"
Requires-Dist: pytest-xdist (>=3.1.0,<4.0.0) ; extra == "test"
Requires-Dist: pytube (>=12.1.2,<13.0.0)
Requires-Dist: questionary (>=1.10.0,<2.0.0)
Requires-Dist: software-patterns (>=2.0.0,<3.0.0)
Requires-Dist: tqdm (>=4.64.1,<5.0.0)
Requires-Dist: youtube_dl (>=2021.12.17,<2022.0.0)
Project-URL: Bug Tracker, https://github.com/boromir674/music-album-creator/issues
Project-URL: CI: Github Actions, https://github.com/boromir674/music-album-creator/actions
Project-URL: Changelog, https://github.com/boromir674/music-album-creator/blob/master/CHANGELOG.rst
Project-URL: Code of Conduct, https://github.com/boromir674/music-album-creator/blob/master/CONTRIBUTING.rst
Project-URL: Documentation, https://music-album-creator.readthedocs.io/
Project-URL: Repository, https://github.com/boromir674/music-album-creator
Project-URL: Source Code, https://github.com/boromir674/music-album-creator
